beyondvcr/__init__.py
beyondvcr/client.py
beyondvcr/server.py
beyondvcr-0.1.1.dist-info/LICENSE
beyondvcr-0.1.1.dist-info/METADATA
beyondvcr-0.1.1.dist-info/WHEEL
beyondvcr-0.1.1.dist-info/top_level.txt
beyondvcr-0.1.1.dist-info/RECORD
