Metadata-Version: 2.1
Name: beyondvcr
Version: 0.1.1
Summary: BeyondVCR helps you to write tests for code that does HTTP calls
Home-page: https://gitlab.com/eliasdorneles/beyondvcr
Author: Elias Dorneles
Author-email: eliasdorneles@gmail.com
License: MIT license
Keywords: beyondvcr
Platform: UNKNOWN
Classifier: Development Status :: 2 - Pre-Alpha
Classifier: Intended Audience :: Developers
Classifier: License :: OSI Approved :: MIT License
Classifier: Natural Language :: English
Classifier: Programming Language :: Python :: 3
Classifier: Programming Language :: Python :: 3.6
Classifier: Programming Language :: Python :: 3.7
Classifier: Programming Language :: Python :: 3.8
Requires-Python: >=3.6
License-File: LICENSE
Requires-Dist: requests
